CHANGELOG
MANIFEST.in
README
setup.py
pyrally/__init__.py
pyrally/client.py
pyrally/models.py
pyrally/rally_access.py
pyrally/register.py
pyrally/settings.py
pyrally.egg-info/PKG-INFO
pyrally.egg-info/SOURCES.txt
pyrally.egg-info/dependency_links.txt
pyrally.egg-info/requires.txt
pyrally.egg-info/top_level.txt
pyrally.egg-info/zip-safe